everai_autoscaler/builtin/__init__.py
everai_autoscaler/builtin/builtin_autoscaler_helper.py
everai_autoscaler/builtin/builtin_manager.py
everai_autoscaler/builtin/free_worker_autoscaler.py
everai_autoscaler/builtin/is_builtin.py
everai_autoscaler/builtin/simple_autoscaler.py
everai_autoscaler/builtin/singleton.py
everai_autoscaler/builtin/decorator/__init__.py
everai_autoscaler/builtin/decorator/arguments/__init__.py
everai_autoscaler/builtin/decorator/arguments/decorator.py
everai_autoscaler/builtin/decorator/arguments/noop.py
everai_autoscaler/builtin/decorator/arguments/time_match.py
everai_autoscaler/builtin/decorator/factors/__init__.py
everai_autoscaler/builtin/decorator/factors/average.py
everai_autoscaler/builtin/decorator/factors/decorator.py
everai_autoscaler/builtin/decorator/factors/noop.py
everai_autoscaler/builtin/factory/__init__.py
everai_autoscaler/builtin/factory/factory.py
everai_autoscaler/builtin/factory/singleton.py
everai_builtin_autoscaler-0.1.52.dist-info/METADATA
everai_builtin_autoscaler-0.1.52.dist-info/WHEEL
everai_builtin_autoscaler-0.1.52.dist-info/entry_points.txt
everai_builtin_autoscaler-0.1.52.dist-info/top_level.txt
everai_builtin_autoscaler-0.1.52.dist-info/RECORD
